Metadata-Version: 1.1
Name: django-email-notification
Version: 1.3
Summary: django-email-notification allows backoffice users to send short email notifications to django registered users or users you only know the email about what is new or changed from django's admin or a dedicated view. And then track their clicks.
Home-page: http://bitbucket.org/rmoch/django-email-notification
Author: Richard Moch
Author-email: richard@rootsaka.com
License: UNKNOWN
Platform: UNKNOWN
Classifier: Development Status :: 5 - Production/Stable
Classifier: Environment :: Web Environment
Classifier: Framework :: Django
Classifier: Intended Audience :: Developers
Classifier: License :: OSI Approved :: MIT License
Classifier: Operating System :: OS Independent
Classifier: Programming Language :: Python
Classifier: Topic :: Internet :: WWW/HTTP
Classifier: Topic :: Utilities
